pdchaoskit/__init__.py
pdchaoskit/cli.py
pdchaoskit/context.py
pdchaoskit/controls.py
pdchaoskit/scripts.py
pdchaoskit/settings.py
pdchaoskit/vcs.py
pdchaoskit/alert/__init__.py
pdchaoskit/alert/probes.py
pdchaoskit/api/__init__.py
pdchaoskit/api/alerts.py
pdchaoskit/api/applications.py
pdchaoskit/api/endpoints.py
pdchaoskit/api/events.py
pdchaoskit/api/executions.py
pdchaoskit/api/experiments.py
pdchaoskit/api/scripts.py
pdchaoskit/api/session.py
pdchaoskit/application/__init__.py
pdchaoskit/application/actions.py
proofdock_chaos_kit-1.0.5.dist-info/LICENSE
proofdock_chaos_kit-1.0.5.dist-info/METADATA
proofdock_chaos_kit-1.0.5.dist-info/WHEEL
proofdock_chaos_kit-1.0.5.dist-info/entry_points.txt
proofdock_chaos_kit-1.0.5.dist-info/top_level.txt
proofdock_chaos_kit-1.0.5.dist-info/RECORD
