Metadata-Version: 2.1
Name: proofdock-chaos-kit
Version: 1.0.5
Summary: Extend the Chaos Toolkit with capabilities for the Proofdock Chaos Engineering Platform
Home-page: https://proofdock.io
Author: Proofdock
Author-email: hello@proofdock.io
License: Apache License Version 2.0
Project-URL: Documentation, https://docs.proofdock.io/
Project-URL: Support, https://github.com/proofdock/chaos-support
Platform: UNKNOWN
Classifier: Intended Audience :: Developers
Classifier: License :: Freely Distributable
Classifier: Operating System :: OS Independent
Classifier: License :: OSI Approved :: Apache Software License
Classifier: Programming Language :: Python
Classifier: Programming Language :: Python :: 3
Classifier: Programming Language :: Python :: 3.5
Classifier: Programming Language :: Python :: 3.6
Classifier: Programming Language :: Python :: 3.7
Classifier: Programming Language :: Python :: 3.8
Classifier: Programming Language :: Python :: Implementation
Classifier: Programming Language :: Python :: Implementation :: CPython
Requires-Python: >=3.5.*
Requires-Dist: chaostoolkit-lib (~=1.15.0)
Requires-Dist: chaostoolkit (~=1.7.0)
Requires-Dist: logzero (==1.5.0)
Requires-Dist: click (~=7.0)
Requires-Dist: tabulate (~=0.8.6)
